ModernJavaAGuideToJava8/README.md
ModernJavaAGuideToJava8/__init__.py
ModernJavaAGuideToJava8/__main__.py
ModernJavaAGuideToJava8/file.epub
ModernJavaAGuideToJava8/index.html
ModernJavaAGuideToJava8/css/__init__.py
ModernJavaAGuideToJava8/css/annotations.css
ModernJavaAGuideToJava8/css/main.css
ModernJavaAGuideToJava8/css/normalize.css
ModernJavaAGuideToJava8/css/popup.css
ModernJavaAGuideToJava8/font/__init__.py
ModernJavaAGuideToJava8/font/fontello.eot
ModernJavaAGuideToJava8/font/fontello.svg
ModernJavaAGuideToJava8/font/fontello.ttf
ModernJavaAGuideToJava8/font/fontello.woff
ModernJavaAGuideToJava8/img/__init__.py
ModernJavaAGuideToJava8/img/annotator-glyph-sprite.png
ModernJavaAGuideToJava8/img/annotator-icon-sprite.png
ModernJavaAGuideToJava8/img/apple-touch-icon.png
ModernJavaAGuideToJava8/img/cancelfullscreen.png
ModernJavaAGuideToJava8/img/close.png
ModernJavaAGuideToJava8/img/fullscreen.png
ModernJavaAGuideToJava8/img/loader.gif
ModernJavaAGuideToJava8/img/menu-icon.png
ModernJavaAGuideToJava8/img/save.png
ModernJavaAGuideToJava8/img/saved.png
ModernJavaAGuideToJava8/img/settings-s.png
ModernJavaAGuideToJava8/img/settings.png
ModernJavaAGuideToJava8/img/star.png
ModernJavaAGuideToJava8/js/__init__.py
ModernJavaAGuideToJava8/js/epub.js
ModernJavaAGuideToJava8/js/epub.min.js
ModernJavaAGuideToJava8/js/epub.min.map
ModernJavaAGuideToJava8/js/hooks.min.js
ModernJavaAGuideToJava8/js/hooks.min.map
ModernJavaAGuideToJava8/js/reader.js
ModernJavaAGuideToJava8/js/reader.js.map
ModernJavaAGuideToJava8/js/reader.min.js
ModernJavaAGuideToJava8/js/reader.min.map
ModernJavaAGuideToJava8/js/hooks/__init__.py
ModernJavaAGuideToJava8/js/hooks/extensions/__init__.py
ModernJavaAGuideToJava8/js/hooks/extensions/highlight.js
ModernJavaAGuideToJava8/js/libs/__init__.py
ModernJavaAGuideToJava8/js/libs/jquery.min.js
ModernJavaAGuideToJava8/js/libs/localforage.min.js
ModernJavaAGuideToJava8/js/libs/screenfull.js
ModernJavaAGuideToJava8/js/libs/screenfull.min.js
modern_java_a_guide_to_java_8-2024.3.1.0.dist-info/METADATA
modern_java_a_guide_to_java_8-2024.3.1.0.dist-info/WHEEL
modern_java_a_guide_to_java_8-2024.3.1.0.dist-info/entry_points.txt
modern_java_a_guide_to_java_8-2024.3.1.0.dist-info/top_level.txt
modern_java_a_guide_to_java_8-2024.3.1.0.dist-info/RECORD
